pymmd/__init__.py
pymmd/defaults.py
pymmd/download.py
pymmd/mmd.py
pymmd/files/libMultiMarkdown.dylib
pymmd-0.4.0.dist-info/DESCRIPTION.rst
pymmd-0.4.0.dist-info/METADATA
pymmd-0.4.0.dist-info/RECORD
pymmd-0.4.0.dist-info/WHEEL
pymmd-0.4.0.dist-info/metadata.json
pymmd-0.4.0.dist-info/top_level.txt
