Metadata-Version: 2.0
Name: pymmd
Version: 0.4.0
Summary: Python wrapper for the MultiMarkdown library.
Home-page: https://github.com/jasedit/pymmd
Author: Jason Ziglar
Author-email: jasedit@gmail.com
License: MIT
Platform: UNKNOWN
Classifier: Development Status :: 3 - Alpha
Classifier: Intended Audience :: Developers
Classifier: Topic :: Text Processing :: Markup
Classifier: Topic :: Text Processing :: Filters
Classifier: Topic :: Software Development :: Libraries :: Python Modules
Classifier: License :: OSI Approved :: MIT License
Classifier: Programming Language :: Python :: 2
Classifier: Programming Language :: Python :: 3
